virtualbmc/__init__.py
virtualbmc/config.py
virtualbmc/control.py
virtualbmc/exception.py
virtualbmc/log.py
virtualbmc/manager.py
virtualbmc/utils.py
virtualbmc/vbmc.py
virtualbmc/cmd/__init__.py
virtualbmc/cmd/vbmc.py
virtualbmc/cmd/vbmcd.py
virtualbmc/tests/__init__.py
virtualbmc/tests/unit/__init__.py
virtualbmc/tests/unit/base.py
virtualbmc/tests/unit/test_config.py
virtualbmc/tests/unit/test_control.py
virtualbmc/tests/unit/test_manager.py
virtualbmc/tests/unit/test_utils.py
virtualbmc/tests/unit/test_vbmc.py
virtualbmc/tests/unit/utils.py
virtualbmc/tests/unit/cmd/__init__.py
virtualbmc/tests/unit/cmd/test_vbmc.py
virtualbmc/tests/unit/cmd/test_vbmcd.py
virtualbmc-3.2.0.dist-info/AUTHORS
virtualbmc-3.2.0.dist-info/LICENSE
virtualbmc-3.2.0.dist-info/METADATA
virtualbmc-3.2.0.dist-info/WHEEL
virtualbmc-3.2.0.dist-info/entry_points.txt
virtualbmc-3.2.0.dist-info/pbr.json
virtualbmc-3.2.0.dist-info/top_level.txt
virtualbmc-3.2.0.dist-info/RECORD
