Metadata-Version: 2.1
Name: virtualbmc
Version: 3.2.0
Summary: Create virtual BMCs for controlling virtual instances via IPMI
Home-page: https://docs.openstack.org/virtualbmc/latest/
Author: OpenStack
Author-email: openstack-discuss@lists.openstack.org
Classifier: Environment :: OpenStack
Classifier: Intended Audience :: Information Technology
Classifier: Intended Audience :: System Administrators
Classifier: License :: OSI Approved :: Apache Software License
Classifier: Operating System :: POSIX :: Linux
Classifier: Programming Language :: Python
Classifier: Programming Language :: Python :: Implementation :: CPython
Classifier: Programming Language :: Python :: 3 :: Only
Classifier: Programming Language :: Python :: 3
Classifier: Programming Language :: Python :: 3.9
Classifier: Programming Language :: Python :: 3.10
Classifier: Programming Language :: Python :: 3.11
Classifier: Programming Language :: Python :: 3.12
Requires-Python: >=3.9
License-File: LICENSE
License-File: AUTHORS
Requires-Dist: pbr !=2.1.0,>=2.0.0
Requires-Dist: libvirt-python >=6.0.0
Requires-Dist: pyghmi >=1.2.0
Requires-Dist: cliff !=2.9.0,>=2.8.0
Requires-Dist: pyzmq >=19.0.0
